sainsc/__init__.py
sainsc/_typealias.py
sainsc/_utils.py
sainsc/_utils_rust.cp311-win_amd64.pyd
sainsc/_utils_rust.pyi
sainsc/datasets.py
sainsc/py.typed
sainsc/io/__init__.py
sainsc/io/_io.py
sainsc/io/_io_utils.py
sainsc/io/_stereoseq_chips.py
sainsc/lazykde/_LazyKDE.py
sainsc/lazykde/__init__.py
sainsc/lazykde/_utils.py
sainsc/utils/__init__.py
sainsc/utils/_kernel.py
sainsc/utils/_signatures.py
sainsc-0.2.1.dist-info/LICENSE
sainsc-0.2.1.dist-info/METADATA
sainsc-0.2.1.dist-info/WHEEL
sainsc-0.2.1.dist-info/top_level.txt
sainsc-0.2.1.dist-info/RECORD
