Metadata-Version: 2.1
Name: sainsc
Version: 0.2.1
Summary: Segmentation-free Analysis of In Situ Capture data
Author-email: Niklas Müller-Bötticher <niklas.mueller-boetticher@charite.de>
License: MIT License
Project-URL: Homepage, https://github.com/HiDiHlabs/sainsc
Project-URL: Documentation, https://sainsc.readthedocs.io
Project-URL: Repository, https://github.com/HiDiHlabs/sainsc
Project-URL: Issues, https://github.com/HiDiHlabs/sainsc/issues
Classifier: Intended Audience :: Science/Research
Classifier: License :: OSI Approved :: MIT License
Classifier: Operating System :: OS Independent
Classifier: Programming Language :: Python
Classifier: Programming Language :: Python :: 3
Classifier: Programming Language :: Python :: 3 :: Only
Classifier: Programming Language :: Python :: Implementation :: CPython
Classifier: Programming Language :: Rust
Classifier: Topic :: Scientific/Engineering :: Bio-Informatics
Classifier: Typing :: Typed
Requires-Python: >=3.10
License-File: LICENSE
Requires-Dist: anndata >=0.9
Requires-Dist: matplotlib
Requires-Dist: matplotlib-scalebar
Requires-Dist: numba >=0.44
Requires-Dist: numpy >=1.21
Requires-Dist: pandas
Requires-Dist: polars[pandas] >=1
Requires-Dist: scikit-image >=0.18
Requires-Dist: scipy >=1.9
Requires-Dist: seaborn >=0.11
Requires-Dist: typing-extensions >=4
Provides-Extra: data
Requires-Dist: pooch >=1 ; extra == 'data'
Provides-Extra: dev
Requires-Dist: sainsc[data,docs,spatialdata] ; extra == 'dev'
Requires-Dist: pre-commit ; extra == 'dev'
Provides-Extra: docs
Requires-Dist: sphinx ; extra == 'docs'
Requires-Dist: sphinx-autoapi >=3.1 ; extra == 'docs'
Requires-Dist: sphinx-copybutton ; extra == 'docs'
Requires-Dist: sphinx-rtd-theme ; extra == 'docs'
Requires-Dist: myst-nb ; extra == 'docs'
Provides-Extra: spatialdata
Requires-Dist: spatialdata >=0.1 ; extra == 'spatialdata'
